coda/.coda
coda/__init__.py
coda/__main__.py
coda/objects.py
coda/db.py
coda-0.1.0.dist-info/WHEEL
coda-0.1.0.dist-info/METADATA
coda-0.1.0.dist-info/metadata.json
coda-0.1.0.dist-info/RECORD
coda-0.1.0.dist-info/top_level.txt
coda-0.1.0.dist-info/DESCRIPTION.rst
coda-0.1.0.dist-info/entry_points.txt
