Metadata-Version: 1.1
Name: coda
Version: 0.1.0
Summary: File metadata tagging and organization.
Home-page: https://github.com/bprinty/coda
Author: Blake Printy
Author-email: bprinty@gmail.com
License: Apache-2.0
Keywords: coda,data,science,analysis,file,organization,metadata
Platform: UNKNOWN
Classifier: Intended Audience :: Developers
Classifier: License :: OSI Approved :: Apache Software License
Classifier: Natural Language :: English
Classifier: Programming Language :: Python :: 2
Classifier: Programming Language :: Python :: 2.6
Classifier: Programming Language :: Python :: 2.7
Classifier: Programming Language :: Python :: 3
Classifier: Programming Language :: Python :: 3.3
Classifier: Programming Language :: Python :: 3.4
